audiossl/__init__.py
audiossl/datasets/__init__.py
audiossl/datasets/byol_a.py
audiossl/datasets/iemocap.py
audiossl/datasets/librispeech.py
audiossl/datasets/lmdb.py
audiossl/datasets/registry.py
audiossl/datasets/voxceleb1.py
audiossl/lightning/__init__.py
audiossl/lightning/datamodules.py
audiossl/lightning/utils.py
audiossl/models/__init__.py
audiossl/models/atst/__init__.py
audiossl/models/atst/atst.py
audiossl/models/atst/audio_transformer.py
audiossl/models/atst/byol.py
audiossl/transforms/__init__.py
audiossl/transforms/byol_a.py
audiossl/transforms/common.py
audiossl/transforms/target_transform.py
audiossl/utils/__init__.py
audiossl/utils/common.py
audiossl/utils/plot.py
audiossl-0.1.dist-info/METADATA
audiossl-0.1.dist-info/WHEEL
audiossl-0.1.dist-info/entry_points.txt
audiossl-0.1.dist-info/top_level.txt
audiossl-0.1.dist-info/RECORD
