Metadata-Version: 2.1
Name: audiossl
Version: 0.1
Summary: UNKNOWN
Home-page: UNKNOWN
Author: lixian
License: UNKNOWN
Platform: UNKNOWN
Requires-Dist: absl-py (==1.0.0)
Requires-Dist: aiohttp (==3.8.1)
Requires-Dist: aiosignal (==1.2.0)
Requires-Dist: alabaster (==0.7.12)
Requires-Dist: antlr4-python3-runtime (==4.8)
Requires-Dist: appdirs (==1.4.4)
Requires-Dist: async-timeout (==4.0.2)
Requires-Dist: asynctest (==0.13.0)
Requires-Dist: attrs (==21.4.0)
Requires-Dist: audioread (==2.1.9)
Requires-Dist: cachetools (==5.0.0)
Requires-Dist: certifi (==2021.10.8)
Requires-Dist: cffi (==1.15.0)
Requires-Dist: charset-normalizer (==2.0.12)
Requires-Dist: click (==8.1.1)
Requires-Dist: colorama (==0.4.4)
Requires-Dist: cycler (==0.11.0)
Requires-Dist: Cython (==0.29.26)
Requires-Dist: dataclasses (==0.6)
Requires-Dist: decorator (==5.1.1)
Requires-Dist: docker-pycreds (==0.4.0)
Requires-Dist: docstring-parser (==0.13)
Requires-Dist: docutils (==0.17.1)
Requires-Dist: efficientnet-pytorch (==0.6.3)
Requires-Dist: einops (==0.4.0)
Requires-Dist: fairseq (==0.10.2)
Requires-Dist: filelock (==3.6.0)
Requires-Dist: fonttools (==4.29.0)
Requires-Dist: frozenlist (==1.3.0)
Requires-Dist: fsspec (==2022.2.0)
Requires-Dist: gitdb (==4.0.9)
Requires-Dist: GitPython (==3.1.27)
Requires-Dist: google-auth (==2.6.2)
Requires-Dist: google-auth-oauthlib (==0.4.6)
Requires-Dist: grpcio (==1.44.0)
Requires-Dist: huggingface-hub (==0.4.0)
Requires-Dist: hydra-core (==1.1.1)
Requires-Dist: idna (==3.3)
Requires-Dist: imageio (==2.16.0)
Requires-Dist: imagesize (==1.3.0)
Requires-Dist: importlib-metadata (==4.11.3)
Requires-Dist: importlib-resources (==5.4.0)
Requires-Dist: Jinja2 (==3.1.1)
Requires-Dist: joblib (==1.1.0)
Requires-Dist: jsonargparse (==4.5.0)
Requires-Dist: kiwisolver (==1.3.2)
Requires-Dist: kornia (==0.6.4)
Requires-Dist: librosa (==0.9.1)
Requires-Dist: lightning-bolts (==0.5.0)
Requires-Dist: lightning-flash (==0.7.2)
Requires-Dist: llvmlite (==0.38.0)
Requires-Dist: lmdb (==1.3.0)
Requires-Dist: Markdown (==3.3.6)
Requires-Dist: MarkupSafe (==2.1.1)
Requires-Dist: matplotlib (==3.5.1)
Requires-Dist: mkl-fft (==1.3.1)
Requires-Dist: mkl-random (==1.2.2)
Requires-Dist: mkl-service (==2.4.0)
Requires-Dist: multidict (==6.0.2)
Requires-Dist: munch (==2.5.0)
Requires-Dist: networkx (==2.6.3)
Requires-Dist: numba (==0.55.1)
Requires-Dist: oauthlib (==3.2.0)
Requires-Dist: omegaconf (==2.1.1)
Requires-Dist: opencv-python (==4.5.5.62)
Requires-Dist: packaging (==21.3)
Requires-Dist: pandas (==1.3.5)
Requires-Dist: pathtools (==0.1.2)
Requires-Dist: pockets (==0.9.1)
Requires-Dist: pooch (==1.6.0)
Requires-Dist: portalocker (==2.3.2)
Requires-Dist: pretrainedmodels (==0.7.4)
Requires-Dist: promise (==2.3)
Requires-Dist: protobuf (==3.19.4)
Requires-Dist: psutil (==5.9.0)
Requires-Dist: pyarrow (==6.0.1)
Requires-Dist: pyasn1 (==0.4.8)
Requires-Dist: pyasn1-modules (==0.2.8)
Requires-Dist: pycparser (==2.21)
Requires-Dist: pyDeprecate (==0.3.2)
Requires-Dist: Pygments (==2.11.2)
Requires-Dist: pyparsing (==3.0.7)
Requires-Dist: pystiche (==1.0.1)
Requires-Dist: python-dateutil (==2.8.2)
Requires-Dist: pytorch-lightning (==1.6.0)
Requires-Dist: pytz (==2021.3)
Requires-Dist: PyWavelets (==1.2.0)
Requires-Dist: PyYAML (==6.0)
Requires-Dist: regex (==2022.1.18)
Requires-Dist: requests (==2.27.1)
Requires-Dist: requests-oauthlib (==1.3.1)
Requires-Dist: resampy (==0.2.2)
Requires-Dist: rsa (==4.8)
Requires-Dist: sacrebleu (==2.0.0)
Requires-Dist: sacremoses (==0.0.49)
Requires-Dist: scikit-image (==0.19.2)
Requires-Dist: scikit-learn (==1.0.2)
Requires-Dist: scipy (==1.7.3)
Requires-Dist: segmentation-models-pytorch (==0.2.1)
Requires-Dist: sentry-sdk (==1.5.8)
Requires-Dist: setproctitle (==1.2.2)
Requires-Dist: shortuuid (==1.0.8)
Requires-Dist: six
Requires-Dist: smmap (==5.0.0)
Requires-Dist: snowballstemmer (==2.2.0)
Requires-Dist: SoundFile (==0.10.3.post1)
Requires-Dist: Sphinx (==4.5.0)
Requires-Dist: sphinxcontrib-applehelp (==1.0.2)
Requires-Dist: sphinxcontrib-devhelp (==1.0.2)
Requires-Dist: sphinxcontrib-htmlhelp (==2.0.0)
Requires-Dist: sphinxcontrib-jsmath (==1.0.1)
Requires-Dist: sphinxcontrib-napoleon (==0.7)
Requires-Dist: sphinxcontrib-qthelp (==1.0.3)
Requires-Dist: sphinxcontrib-serializinghtml (==1.1.5)
Requires-Dist: tabulate (==0.8.9)
Requires-Dist: tensorboard (==2.8.0)
Requires-Dist: tensorboard-data-server (==0.6.1)
Requires-Dist: tensorboard-plugin-wit (==1.8.1)
Requires-Dist: termcolor (==1.1.0)
Requires-Dist: threadpoolctl (==3.1.0)
Requires-Dist: tifffile (==2021.11.2)
Requires-Dist: timm (==0.4.12)
Requires-Dist: tokenizers (==0.11.6)
Requires-Dist: toml
Requires-Dist: torch (==1.10.1)
Requires-Dist: torchaudio (==0.10.1)
Requires-Dist: torchmetrics (==0.7.3)
Requires-Dist: torchvision (==0.11.2)
Requires-Dist: tqdm (==4.62.3)
Requires-Dist: transformers (==4.17.0)
Requires-Dist: urllib3 (==1.26.8)
Requires-Dist: wandb (==0.12.11)
Requires-Dist: Werkzeug (==2.1.0)
Requires-Dist: yarl (==1.7.2)
Requires-Dist: yaspin (==2.1.0)
Requires-Dist: zipp (==3.7.0)
